azureml/rag/__init__.py
azureml/rag/_constants.py
azureml/rag/docstore.py
azureml/rag/mlindex.py
azureml/rag/models.py
azureml/rag/_asset_client/client.py
azureml/rag/_asset_client/_restclient/__init__.py
azureml/rag/_asset_client/_restclient/_azure_machine_learning_workspaces.py
azureml/rag/_asset_client/_restclient/_configuration.py
azureml/rag/_asset_client/_restclient/_patch.py
azureml/rag/_asset_client/_restclient/_version.py
azureml/rag/_asset_client/_restclient/models.py
azureml/rag/_asset_client/_restclient/dataset/__init__.py
azureml/rag/_asset_client/_restclient/dataset/_azure_machine_learning_workspaces.py
azureml/rag/_asset_client/_restclient/dataset/_configuration.py
azureml/rag/_asset_client/_restclient/dataset/_patch.py
azureml/rag/_asset_client/_restclient/dataset/_serialization.py
azureml/rag/_asset_client/_restclient/dataset/_vendor.py
azureml/rag/_asset_client/_restclient/dataset/_version.py
azureml/rag/_asset_client/_restclient/dataset/py.typed
azureml/rag/_asset_client/_restclient/dataset/models/__init__.py
azureml/rag/_asset_client/_restclient/dataset/models/_azure_machine_learning_workspaces_enums.py
azureml/rag/_asset_client/_restclient/dataset/models/_models_py3.py
azureml/rag/_asset_client/_restclient/dataset/models/_patch.py
azureml/rag/_asset_client/_restclient/dataset/operations/__init__.py
azureml/rag/_asset_client/_restclient/dataset/operations/_data_version_operations.py
azureml/rag/_asset_client/_restclient/dataset/operations/_mlindex_operations.py
azureml/rag/_asset_client/_restclient/runhistory/__init__.py
azureml/rag/_asset_client/_restclient/runhistory/_azure_machine_learning_workspaces.py
azureml/rag/_asset_client/_restclient/runhistory/_configuration.py
azureml/rag/_asset_client/_restclient/runhistory/_patch.py
azureml/rag/_asset_client/_restclient/runhistory/_vendor.py
azureml/rag/_asset_client/_restclient/runhistory/_version.py
azureml/rag/_asset_client/_restclient/runhistory/py.typed
azureml_rag-0.2.39.1.dist-info/licenses/LICENSE.txt
azureml_rag-0.2.39.1.dist-info/METADATA
azureml_rag-0.2.39.1.dist-info/WHEEL
azureml_rag-0.2.39.1.dist-info/top_level.txt
azureml_rag-0.2.39.1.dist-info/RECORD
