Metadata-Version: 2.4
Name: azureml-rag
Version: 0.2.39.1
Summary: Contains Retrieval Augmented Generation related utilities for Azure Machine Learning and OSS interoperability.
Home-page: https://docs.microsoft.com/python/api/overview/azure/ml/?view=azure-ml-py
Author: Microsoft Corporation
License: Proprietary https://aka.ms/azureml-preview-sdk-license 
Classifier: Development Status :: 5 - Production/Stable
Classifier: Intended Audience :: Developers
Classifier: Intended Audience :: Science/Research
Classifier: License :: Other/Proprietary License
Classifier: Programming Language :: Python
Classifier: Programming Language :: Python :: 3 :: Only
Classifier: Programming Language :: Python :: 3.9
Classifier: Programming Language :: Python :: 3.10
Classifier: Programming Language :: Python :: 3.11
Classifier: Programming Language :: Python :: 3.12
Classifier: Operating System :: MacOS
Classifier: Operating System :: Microsoft :: Windows
Classifier: Operating System :: POSIX :: Linux
Classifier: Topic :: Scientific/Engineering
Requires-Python: >=3.9,<4.0
License-File: LICENSE.txt
Requires-Dist: azureml-dataprep[parquet]>=5.1
Requires-Dist: azureml-fsspec
Requires-Dist: fsspec~=2023.3
Requires-Dist: openai>=0.27.8
Requires-Dist: tiktoken<1.0,>=0.7
Requires-Dist: cloudpickle
Requires-Dist: mmh3
Requires-Dist: pyyaml<7.0.0,>=5.1.0
Requires-Dist: requests
Requires-Dist: azureml-core~=1.60
Provides-Extra: azure
Requires-Dist: azure-ai-ml<2.0.0,>=1.23.0; extra == "azure"
Requires-Dist: azure-identity>=1.17.0; extra == "azure"
Provides-Extra: azureml-core
Requires-Dist: azureml-core; extra == "azureml-core"
Requires-Dist: azureml-telemetry; extra == "azureml-core"
Requires-Dist: azureml-mlflow; extra == "azureml-core"
Provides-Extra: faiss
Requires-Dist: faiss-cpu; extra == "faiss"
Provides-Extra: cognitive-search
Requires-Dist: azure-search-documents>=11.4.0; extra == "cognitive-search"
Provides-Extra: pinecone
Requires-Dist: pinecone-client<7.0.0,>=6.0.0; extra == "pinecone"
Requires-Dist: langchain-pinecone<0.3.0,>=0.2.0; extra == "pinecone"
Provides-Extra: azure-cosmos-mongo-vcore
Requires-Dist: pymongo; extra == "azure-cosmos-mongo-vcore"
Provides-Extra: azure-cosmos-nosql
Requires-Dist: azure-cosmos>=4.7.0; extra == "azure-cosmos-nosql"
Provides-Extra: milvus
Requires-Dist: pymilvus>=2.3.0; extra == "milvus"
Provides-Extra: mongodb
Requires-Dist: pymongo; extra == "mongodb"
Provides-Extra: elasticsearch
Requires-Dist: elasticsearch<9.0,>=8.12.0; extra == "elasticsearch"
Provides-Extra: weaviate
Requires-Dist: weaviate-client>=4.0.0; extra == "weaviate"
Provides-Extra: qdrant
Requires-Dist: qdrant-client<2.0.0,>=1.8.0; extra == "qdrant"
Requires-Dist: langchain-qdrant; extra == "qdrant"
Provides-Extra: hugging-face
Requires-Dist: scikit-learn; extra == "hugging-face"
Requires-Dist: sentence-transformers; extra == "hugging-face"
Requires-Dist: huggingface-hub>=0.25.1; extra == "hugging-face"
Provides-Extra: langchain
Requires-Dist: langchain<0.4.0,>=0.3.0; extra == "langchain"
Requires-Dist: langchain-community<0.4.0,>=0.3.0; extra == "langchain"
Provides-Extra: document-parsing
Requires-Dist: pandas>=1; extra == "document-parsing"
Requires-Dist: nltk~=3.9.1; extra == "document-parsing"
Requires-Dist: markdown; extra == "document-parsing"
Requires-Dist: beautifulsoup4~=4.11.2; extra == "document-parsing"
Requires-Dist: tika~=2.6.0; extra == "document-parsing"
Requires-Dist: pypdf~=3.17.1; extra == "document-parsing"
Requires-Dist: unstructured; extra == "document-parsing"
Requires-Dist: GitPython>=3.1; extra == "document-parsing"
Requires-Dist: azure-ai-formrecognizer; extra == "document-parsing"
Provides-Extra: data-generation
Requires-Dist: pandas>=1; extra == "data-generation"
Requires-Dist: beautifulsoup4~=4.11.2; extra == "data-generation"
Requires-Dist: lxml~=4.9.2; extra == "data-generation"
Requires-Dist: azure-ai-ml<2.0.0,>=1.23.0; extra == "data-generation"
Provides-Extra: remote-tests
Requires-Dist: pytest; extra == "remote-tests"
Requires-Dist: pytest-xdist; extra == "remote-tests"
Requires-Dist: azure-ai-ml<2.0.0,>=1.23.0; extra == "remote-tests"
Requires-Dist: azure-cli; extra == "remote-tests"
Requires-Dist: azure-core!=1.22.0,<2.0.0,>=1.8.0; extra == "remote-tests"
Requires-Dist: azure-mgmt-core<2.0.0,>=1.3.0; extra == "remote-tests"
Requires-Dist: azure-keyvault-secrets>=4.6.0; extra == "remote-tests"
Provides-Extra: local-tests
Requires-Dist: pytest; extra == "local-tests"
Requires-Dist: wikipedia; extra == "local-tests"
Requires-Dist: pytest-cov; extra == "local-tests"
Provides-Extra: validate-deployments
Requires-Dist: azure-mgmt-cognitiveservices>13.0.0; extra == "validate-deployments"
Dynamic: author
Dynamic: classifier
Dynamic: description
Dynamic: description-content-type
Dynamic: home-page
Dynamic: license
Dynamic: license-file
Dynamic: provides-extra
Dynamic: requires-dist
Dynamic: requires-python
Dynamic: summary
